setup_client.py
client/__init__.py
client/client.py
client/client/__init__.py
client/client/add_contact.py
client/client/del_contact.py
client/client/main_window.py
client/client/main_window_conv.py
client/client/start_dialog.py
client/client/transport.py
client/common/__init__.py
client/common/decos.py
client/common/descriptors.py
client/common/errors.py
client/common/metaclasses.py
client/common/utils.py
client/common/variables.py
client/db/__init__.py
client/db/db_client.py
pse_messanger_client.egg-info/PKG-INFO
pse_messanger_client.egg-info/SOURCES.txt
pse_messanger_client.egg-info/dependency_links.txt
pse_messanger_client.egg-info/requires.txt
pse_messanger_client.egg-info/top_level.txt