Metadata-Version: 2.1
Name: pse-messanger-client
Version: 0.0.1
Summary: messanger_client
Home-page: UNKNOWN
Author: Sergey Pedchenko
Author-email: pedchenko.sergey@gmail.com
License: UNKNOWN
Platform: UNKNOWN
